{
	"required": true,
	"package": "net.louis.overhaulmod.mixin",
	"compatibilityLevel": "JAVA_21",
	"mixins": [
		"HorseAccessor",
		"CatAccessor",
		"ArmorStandEntityAccessor",
		"ArrowEntityAccessor",
		"BrushableBlockEntityAccessor",
		"PersistentProjectileEntityAccessor",
		"RecipeManagerAccessor",
		"LivingEntityAccessor",

		"LivingEntityMixin",
		"BundleContentsComponentMixin",
		"BrewingRecipeRegistryMixin",
		"AbstractBlockMixin",
		"HorseAccessor",
		"EnderPearlEntityMixin",
		"WolfEntityMixin",
		"CatEntityMixin",
		"ParrotEntityMixin",
		"ServerPlayerTickMixin",
		"ArmorStandMixin",
		"ItemFrameMixin",
		"ArrowEntityMixin",
		"ItemsMixin",
		"FarmlandBlockMixin",
		"CauldronBehaviorMixin",
		"ItemMixin",
		"ProjectileEntityMixin",
		"EntityMixin",
		"ArrowItemMixin",
		"RecipeManagerMixin",
		"SculkCatalystBlockEntityMixin",
		"ArmorMaterialMixin",
		"LeavesBlockMixin",
		"AbstractMinecartEntityMixin"
	],
	"injectors": {
		"defaultRequire": 1
	},
	"overwrites": {
		"requireAnnotations": true
	}
}